b3/__init__.py
b3/_version.py
b3/exceptions.py
b3/utils.py
b3/datatypes/__init__.py
b3/datatypes/company.py
b3/datatypes/contract_correction.py
b3/datatypes/daily_bulletin.py
b3/datatypes/market.py
b3/datatypes/quotes.py
b3/datatypes/specification.py
b3/net/__init__.py
b3/net/query.py
b3/parsing/__init__.py
b3/parsing/historical_quotes.py
pybov-0.1.2.dist-info/LICENSE
pybov-0.1.2.dist-info/METADATA
pybov-0.1.2.dist-info/WHEEL
pybov-0.1.2.dist-info/top_level.txt
pybov-0.1.2.dist-info/RECORD
