Metadata-Version: 2.1
Name: pybov
Version: 0.1.2
Summary: Python library for processing data from B3
Home-page: https://github.com/glourencoffee/pybov/
Author: Giovanni Lourenço
Author-email: gvnl.developer@outlook.com
License: MIT
Keywords: investment,finances
Requires-Python: >=3.7
License-File: LICENSE
